{
  "aboutTitle": "À propos",
  "addAddresses": "Ajouter des adresses",
  "addCategory": "Ajouter une nouvelle catégorie",
  "addColor": "Ajouter une nouvelle couleur",
  "addEmployee": "Ajouter de nouveaux employés",
  "additionalInformation": "Information supplémentaire",
  "addNew": "Ajouter nouveau",
  "addNewSize": "Ajouter une nouvelle taille",
  "address": "Adresse",
  "addresses": "Adresses",
  "addSchedule": "Ajouter un nouvel horaire",
  "addScheduleTitle": "Ajouter un horaire",
  "addToCart": "Ajouter au panier",
  "alert": "Alerte",
  "all": "Tout",
  "ok": "d'accord",
  "amount": "Montant",
  "amountPaid": "Montant payé",
  "appointment": "Rendez-vous requis",
  "appointmentFailed": "Échec du rendez-vous",
  "appointmentFor": "Votre rendez-vous pour",
  "appointmentInfoTitle": "Informations sur les rendez-vous",
  "appointmentRequired": "Rendez-vous requis",
  "appointmentTitle": "Rendez-vous",
  "area": "Région",
  "availableDates": "Dates disponibles",
  "AvailablePickupfromHome": "Offrez-vous un service de ramassage à domicile?",
  "availableSlots": "Créneaux disponibles",
  "basketTitle": "Panier",
  "bookAppointment": "Prendre rendez-vous",
  "booked": " Le rendez-vous a été pris",
  "bookedSlots": "Créneaux réservés",
  "bookedTitle": "Rendez-vous pris",
  "bookingDates": "Dates de réservation",
  "buy": "Acheter",
  "buyer": "Acheteur",
  "buyFrom": "Ajouter des articles de ce fournisseur",
  "buyNow": "Acheter maintenant",
  "byKeyword": "Sélectionner par mots-clés",
  "cancel": "Annuler",
  "cancelAppointment": "Annuler rendez-vous",
  "cancelAppointmentText": "Voulez-vous vraiment annuler ce rendez-vous?",
  "Cancelled": "Annulé",
  "card": "CARTE",
  "cart": "Panier",
  "cartMsg": "Le produit est déjà ajouté au panier.",
  "cartTitle": "Panier",
  "categories": "Catégories",
  "categoriesTitle": "Catégories",
  "category": "Choisir une catégorie",
  "categoryName": "Nom de catégorie",
  "changeAddress": "Modifier votre adresse",
  "changeOrder": "Voulez-vous vraiment modifier le statut de la commande?",
  "chatTitle": "Discuter en ligne",
  "checkout": "Caisse",
  "checkoutTitle": "Caisse",
  "clean": "Nettoyer ma maison",
  "Clear": "Effacer",
  "close": "Fermeture",
  "closingRequired": "l'heure de fermeture est un champ obligatoire",
  "closingTime": "Heure de fermeture",
  "cod": "PAIEMENT À LA LIVRAISON",
  "color": "Couleur:",
  "colorCode": "Code couleur:",
  "colorName": "Nom de la couleur",
  "colors": "Couleurs",
  "colorsTitle": "Couleurs",
  "commission": "Commission",
  "completed": "Terminé",
  "confirm": "Confirmer le mot de passe",
  "confirmation": "Confirmation",
  "confirmed": "confirmé",
  "Confirmed": "Confirmé",
  "confirmedFor": "Confirmé pour",
  "confirmOrder": "Confirmation de commande",
  "confirmOrderStatus": "Statut de la commande",
  "confirmOrderStatusDetails": "Modifier le statut de la command",
  "confirmOrderText": "Votre mode de paiement est Paiement à la livraison. Veuillez confirmer pour poursuivre la commande",
  "confirmTitle": "Confirmer",
  "contactUs": "Nous contacter",
  "contactUsTitle": "Nous contacter",
  "continue": "Continuez",
  "continueText": "OU continuer avec",
  "couponCode": "Code promo",
  "couponError": "Veuillez entrer le code promo",
  "create": "Créer",
  "createFailed": "Échec de la création.",
  "Decline": "Refuser",
  "declineOrder": "Refuser la commande",
  "delete": "Supprimer",
  "deleteAddress": "Supprimer l'adresse",
  "deleteAddressText": "Voulez-vous vraiment supprimer cette adresse?",
  "deleteColor": "Supprimer la couleur",
  "deleteColorMsg": "Voulez-vous vraiment supprimer cette couleur?",
  "deleteEmployee": "Enlever l'employé",
  "deleteEmployeeText": "Êtes-vous sûr de vouloir enlever votre employé?",
  "deleteFailed": "Échec de la suppression.",
  "deleteImg": "'Supprimer l'image",
  "deleteImgText": "Voulez-vous vraiment supprimer cette image de ce produit?",
  "deleteProduct": "Supprimer le produit",
  "deleteProductText": "Voulez-vous vraiment supprimer ce produit?",
  "deleteService": "Supprimer le service",
  "deleteServiceText": "Voulez-vous vraiment supprimer ce service?",
  "deleteSize": "Supprimer la taille",
  "deleteSizeMsg": "Voulez-vous vraiment supprimer cette taille?",
  "Delivered": "Livré",
  "deliveryAddress": "Sélectionnez l'adresse de livraison",
  "DeliveryService": "Livraison [À cette adresse]",
  "DeliveryServiceAtHome": "Offrez-vous un service de livraison à domicile?",
  "description": "Description",
  "designation": "Désignation",
  "discount": "Rabais",
  "Discount": "Rabais",
  "discountAvailable": "Rabais disponible",
  "discountValue": "Valeur du rabais",
  "distance": "Distance",
  "done": "Fait",
  "edit": "Modifier",
  "editProfileTitle": "Modifier le profil",
  "editSchedule": "Modifier l'horaire",
  "elaborateYourIssue": "Préciser la question",
  "electric": "Travaux électriques",
  "email": "Adresse e-mail",
  "emailAddress": "E-mail",
  "emp": "EMP",
  "employee": "Sélectionnez l'employé",
  "employees": "Employés",
  "employeesTitle": "Employés",
  "employeeText": "Employé",
  "emptyField": "Le champ est vide",
  "emptyFieldMsg": "Veuillez sélectionner le téléphone ou l'e-mail pour réinitialiser votre mot de passe.",
  "enableNotifications": "Activer les notifications",
  "entries": "entrées",
  "expiry": "Date d'expiration",
  "expressDelivery": "Livraison express",
  "extraFeeDescription": "Description des frais supplémentaires",
  "extraFeesPaid": "Frais supplémentaires payés",
  "extraPaymentdescription": "Description du paiement supplémentaire",
  "extraServiceFees": "Frais de service supplémentaires",
  "failed": "Manqué",
  "Failed": "Manqué",
  "failedMsg": "vous avez entré de mauvaises informations d'identification",
  "failedOtp": "Impossible d'envoyer otp",
  "failedToDelete": "impossible de supprimer l'adresse",
  "failedWith": "Échec de la connexion avec",
  "faqsTitle": "FAQ",
  "featured": "En vedette",
  "filter": "Filtre",
  "filterByTags": "Filtrer par balises",
  "filterProvider": "Filtrer les fournisseurs",
  "filters": "Filtres",
  "finishTime": "Heure de fin ",
  "fix": "Réparer mes appareils",
  "forgot": "Mot de passe oublié",
  "forgotText": "Nous sommes là pour vous aider. Indiquez-nous votre adresse e-mail ou votre numéro de téléphone et nous vous enverrons un code PIN à 6 chiffres pour vérification afin de réinitialiser votre mot de passe.",
  "forgotTitle": "Mot de passe oublié",
  "from": "Depuis",
  "greaterOpening": "l'heure de fermeture doit être supérieure à l'heure d'ouverture.",
  "guestText": "Explorer en tant qu'invité",
  "hello": "Bonjour ",
  "hey": "Hé",
  "home": "Domicile",
  "homeAddress": "Adresse du domicile",
  "images": "Images",
  "InProgress": "En cours",
  "invalidAccount": "Type de compte invalide",
  "invalidAccountText": "Vous êtes actuellement connecté en tant que fournisseur. Passez en mode acheteur.",
  "invalidCode": "Code de vérification invalide",
  "invalidCodeMsg": "Veuillez renvoyer le SMS du code de vérification et assurez-vous d'utiliser le code de vérification fourni par l'utilisateur",
  "invalidCoupon": "Coupon non valide, veuillez entrer un code de coupon valide",
  "invalidPhone": "Le numéro de téléphone est invalide",
  "invoiceNumber": "Numéro de facture",
  "items": "Domicile",
  "itemsTitle": "Articles",
  "label": "Étiqueter",
  "laundry": "Laver mes vêtements",
  "limitExceeded": "Limite dépassée",
  "liveUrl": "URL de localisation en direct",
  "loadTemplate": "Charger le modèle",
  "loadTemplates": "Charger le modèle",
  "location": "Emplacement",
  "locationat": "Emplacement au",
  "login": "Connexion",
  "loginFailed": "Échec de la connexion",
  "loginWith": "Se connecter avec",
  "logout": "Se déconnecter",
  "map": "Carte",
  "message": "Message",
  "missingFields": "Champs manquants",
  "myProfile": "Mon profil",
  "mySchedule": "Mon horaire",
  "name": "Nom complet",
  "name1": "Nom",
  "nameError": "Veuillez entrer votre nom",
  "no": "Non",
  "noAccount": "Vous n'avez pas de compte?",
  "noAddress": "le bureau et l'adresse du domicile ne sont pas trouvés, le produit ou le service ne s'affichera pas du côté de l'acheteur.",
  "noAppointment": "Aucun rendez-vous trouvé...",
  "noChat": "Pas d'historique de chat...",
  "noEmployees": "Aucun employé...",
  "noImage": "Pas d'image",
  "noInternet": "Veuillez vérifier votre connexion à Internet et réessayer",
  "noInternet1": "Pas de connexion Internet",
  "noInternet1Msg": "Pas de connexion Internet. Connectez-vous à Internet et réessayez.",
  "noOfAddresses": "Nombre d'adresses :",
  "noOfAppointments": "Nombre de plages de rendez-vous",
  "noOfEmployees": "Nombre d'employés:",
  "noOfProducts": "Nombre de produits :",
  "noOfServices": "Nombre de prestations de service :",
  "noOrder": "Aucune commande trouvée.",
  "noPayments": "Aucun historique de paiement",
  "noProduct": "Aucun produit",
  "noReviews": "Aucun avis",
  "noSchedule": "Aucun horaire",
  "noSearch": "Aucune recherche trouvée",
  "noService": "Aucun service trouvé...",
  "noServices": "Aucun service",
  "notificationsTitle": "Notifications",
  "officeAddress": "Adresse de bureau",
  "onsite": "Sur place",
  "onTheWay": "En route",
  "onTheWayDelivery": "Livraison en cours de route",
  "onTheWayPickUp": "Ramassage en route",
  "openingRequired": "l'heure d'ouverture est un champ obligatoire",
  "openingTime": "Horaire d'ouverture",
  "OR": "OU",
  "or": "ou",
  "order": "Commande",
  "orderCompleted": "Commande terminée",
  "orderConfirmed": "Commande confirmée",
  "orderDelivered": "Commande livrée",
  "orderDetails": "Détails de la commande",
  "orderFailed": "Échec de la création de la commande",
  "orderFailed1": "Échec de la commande",
  "orderFailedMsg": "La création de la commande a échoué, veuillez réessayer plus tard !",
  "orderId": "Numéro de commande",
  "OrderInProgress": "Commande en cours",
  "OrderReadyForPickUp": "Commande prête à être récupérée",
  "orderReceived": "Commande reçue",
  "orderReview": "Examen de la commande",
  "orders": "Commandes",
  "orderStatus": "Statut de la commande",
  "orderSuccess": "Commande passée avec succès",
  "orderType": "Type de commande :",
  "otp": "OTP",
  "otpMsg": "Nous avons envoyé un code à 6 chiffres à votre ",
  "paint": "Peindre ma maison",
  "password": "Entrer le mot de passe",
  "password1": "Mot de passe",
  "passwordChanged": "Mot de passe changé!",
  "passwordChangedMsg": "Votre mot de passe a été changé avec succès.",
  "passwordFailed": "La réinitialisation du mot de passe a échoué !",
  "pay": "Payer",
  "payableAmount": "Montant payable",
  "payingTaxes": "Payez-vous des taxes",
  "payment": "Paiement",
  "paymentConf": "Erreur de confirmation de paiement",
  "paymentCurrentlyPending": "Paiement actuellement en attente",
  "paymentError": "Erreur de confirmation de paiement",
  "paymentFailed": "Le paiement a échoué",
  "payments": "Paiements",
  "paymentsTitle": "Paiements",
  "paymentSuccess": "Paiement réussi",
  "paymentType": "Type de paiement",
  "pending": "En attente",
  "Pending": "En attente",
  "phone": "Téléphoner",
  "phoneNumber": "Numéro de téléphone",
  "pickup": "Ramassage chez le fournisseur",
  "pickUpAddress": "Adresse de ramassage",
  "PickupService": "Ramasser (de cette adresse)",
  "plumbing": "Travaux de plomberie",
  "price": "Prix",
  "priceLabel": "Prix:",
  "priceType": "Type de prix",
  "product": "Produit",
  "productFailed": "Impossible de créer un nouveau produit.",
  "products": "Produits",
  "profile": "Profil",
  "progress": "Progrès",
  "provider": "Fournisseur",
  "providerReview": "Avis sur le fournisseur",
  "providerReviewText": "Rédiger un avis pour le fournisseur",
  "radius": "Rayon de service(KM)",
  "rating": "Évaluation:",
  "ReadyForDelivery": "Prêt pour la livraison",
  "ReadyForPickUp": "Prêt pour le ramassage",
  "Recieved": "Reçu",
  "refund": "Rembourser",
  "refundrequested": "Remboursement demandé",
  "refundSuccess": "Votre demande de remboursement a été placée avec succès",
  "refundTitle": "Demande de remboursement",
  "register": "S'inscrire maintenant!",
  "registerTitle": "Créer un compte",
  "registrationFailed": "Échec de l’inscription",
  "registrationSuccess": "Inscription réussie",
  "registrationSuccessMsg": "Félicitations, votre compte a été créé.",
  "requestCategory": "Demander une nouvelle catégorie",
  "requestDone": "Demande effectuée",
  "requestFailed": "Échec de la demande",
  "requestFailedMsg": "Veuillez entrer une adresse valide du Canada",
  "requiredArea": "la zone est un champ obligatoire",
  "resetText": "Entrez votre nouveau mot de passe et confirmez le mot de passe pour le réinitialiser.",
  "resetTitle": "Réinitialiser le mot de passe",
  "review": "Commentaires",
  "reviews": "Mes avis",
  "reviews1": "Commentaires",
  "save": "Sauvegarder",
  "saveTemplate": "Enregistrer le modèle",
  "scheduleAppointment": "Planifier des rendez-vous",
  "scheduleList": "Liste des horaires",
  "scheduleTitle": "Mon horaire",
  "search": "Recherche",
  "searchServices": "Recherche de services et de produits",
  "searchTags": "Recherche de balises",
  "selectAddress": "Sélectionnez l'adresse",
  "selectAll": "Tout sélectionner",
  "selectCategory": "Choisir une catégorie",
  "selectColor": "Choisir la couleur",
  "selectDate": "Sélectionner une date",
  "SelectProductDelivery": "Sélectionnez la livraison du produit",
  "SelectServiceDelivery": "Sélectionnez la prestation de services",
  "selectTime": "Sélectionnez l'heure",
  "sendAgain": "Envoyer à nouveau",
  "service": "Service",
  "serviceFailed": "Échec de la création d'un nouveau service.",
  "services": "service",
  "shippingInfo": "Vos informations d'expédition",
  "shopDashboard": "Tableau de bord de la boutique",
  "shopItems": "Articles",
  "shopTitle": "Tableau de bord de la boutique",
  "showResult": "Montrer les résultats",
  "showResults": "Montrer les résultats",
  "signIn": "S'identifier",
  "size": "Taille:",
  "sizeName": "Nom de la taille",
  "sizes": "Sélectionnez les tailles",
  "sizes1": "Tailles",
  "sizesTitle": "Tailles",
  "slotsError": "'Erreur d'emplacements",
  "slotTiming": "Synchronisation de chaque créneau",
  "sort": "Trier",
  "standardDelivery": "Livraison Standard",
  "StandardDelivery": "Livraison Standard",
  "submit": "Soumettre",
  "subscriptionTitle": "Abonnements",
  "success": "Succès",
  "successfulWith": "Connexion réussie avec",
  "summary": "Résumé et spécifications",
  "switch": "Changer de langue",
  "switchTo": "Basculer vers ",
  "Taxes": "Taxes",
  "terms": "Conditions et modalités",
  "Terms": "Conditions et modalités",
  "termsText": "En vous inscrivant, vous acceptez nos ",
  "thanks": "NON MERCI",
  "thankyou": "Merci d'avoir acheté via CTRL FIND. Votre commande a été transmise au fournisseur pour validation. Vous recevrez une notification une fois qu'elle sera confirmée.",
  "thankyoupayment": "Merci pour votre paiement! Votre paiement a été validé.",
  "to": "Pour",
  "total": "Total",
  "totalPayment": "Paiement total :",
  "totalSlots": "Nombre total d'emplacements",
  "tracking": "Suivi",
  "trackingDisabled": " Le suivi n'est pas activé",
  "trackingTitle": "Suivi de commande",
  "trackLocation": "Suivre l'emplacement du conducteur",
  "trusted": "De confiance",
  "update": "Mise à jour",
  "updateFailed": "Échec de mise à jour.",
  "updateProfile": "Mettre à jour le profil",
  "upload": "Télécharger",
  "uploadImg": "Importer des images",
  "validity": "Validité jusqu'à",
  "validityLabel": "Validité:",
  "verificationText": " Nous avons envoyé un code PIN à 6 chiffres à votre numéro de téléphone ou à votre e-mail à des fins de vérification",
  "verificationTitle": "Vérification OTP",
  "verify": "Vérifier",
  "waitExtraFees.": "Attendre que le client paie des frais supplémentaires.",
  "welcomeText": "Veuillez vous connecter avec votre numéro de téléphone et votre mot de passe pour continuer.",
  "welcomeTitle": "Content de te revoir!",
  "writeReview": "Écrire un un commentaire",
  "yes": "Oui",
  "YouCanBookMultipleSlots": "vous pouvez réserver plusieurs créneaux.",
  "Hey": "Hé",
  "Browse": "Parcourir",
  "No Reviews": "Pas d'avis",
  "homeaddress": "Adresse Domicile",
  "officeaddress": "Adresse Bureau",
  "Apartmentnumber": "Numéro d'appartment",
  "Suitenumber": "Numéro du suite",
  "addyourthoughts": "Ajoutez vos avis et expériences relatives à ce produit…",
  "NoNotification": "Pas de notifications.",
  "Completeyourprofile": "Completez votre profile",
  "Serviceprovider": "Fournisseur de services",
  "guest": "Invité",
  "PSTnumber": "TVQ",
  "GSTnumber": "TPS/TVH",
  "Companyregistration": "Enregistrement de la société",
  "Provinces": "Provinces",
  "gstpstCheck": "En cochant cette case, vous validez que la validité des informations saisies est à vos risques et périls",
  "noAppointments": "Pas de rendez-vous.",
  "Declined": "Refusé",
  "Deliver": "Livrer",
  "toclient": "A client",
  "Pickup": "Retrait en magasin",
  "fromclient": "Du client",
  "Confirmnow": "Confirmez",
  "Paynow": "Payez",
  "paymentcurrentlypending": "Payment actuellement en attente",
  "Order Update": "Mise à jour de la commande",
  "Order Confirmed": "Commande Confirmée",
  "New Order": "Nouvelle Commande",
  "DiscountedPrice": "Prix escompté:",
  "editProfileAlert": " À des fins de vérification d'identité, veuillez fournir une copie de votre carte d'identité et un spécimen de chèque à verification@ctrlfind.ca. Votre compte ne sera activé qu'à réception et validation de celui-ci.",
  "updateEmployee": "Mettre à jour l'employé",
  "cardHolderName": "Nom du titulaire",
  "PhoneNumber": "Numéro de Téléphone",
  "ItemsTotal": "Total",
  "totalBeforeTax": "Total avant Taxes",
  "Estimated": "Estimé",
  "Coupon": "Coupon",
  "identityVerified": "Identité vérifiée",
  "cancelOrder": "Annuler la commande",
  "Isthisitemtaxable": "Cet article est-il imposable?",
  "selectAddTags": "Selectionner/Ajouter des mots clés",
  //  Alerts Translatio

  "Selectimage": "Selectionner l'image...",
  "Takephoto": "Prenez une photo",
  "Chooselibrary": "Choisir",
  "Selectavatar": "Selectionner l'avatar...",
  "Areyousure": "Etes-vous sûr?",
  "cancelorder": "Voulez-vous annuler la commande?",
  "ConfirmOrder": "Confirmer la commande",
  "thepayableamount": "Le montant à payer est",
  "confirmtoproceed": "Veuillez confirmer pour procéder.",
  "CONFIRM": "CONFIRMER",
  "DECLINE": "REFUSER",
  "NO": "NON",
  "YES": "OUI",
  "ConfirmPayment": "Confirmer le paiement",
  "Order": "Commande",
  "ORDERDETAIL": "DETAIL DE LA COMMANDE",
  "SwitchtoPROVIDER": "Changer à FOURNISSEUR!",
  "errorwhilegettingslots": "erreur lors de l'obtention des créneaux. Cette date n'est pas valide.",
  "schedulealreadybooked": "Cet horaire est déjà réservé, il ne peut pas être modifié/supprimé",
  "successfuloperation": "Opération réussie",
  "filedownloaded": "Le fichier a été téléchargé avec succès.",
  "StoragePermission": "Autorisation de stockage requise",
  "Appaccessstorage": "L'application a besoin d'accéder à votre espace de stockage pour télécharger le fichier",
  "Photoaccessstorage": "L'application doit accéder à votre espace de stockage pour télécharger des photos",
  "PermissionNotGranted": "Autorisation de stockage non accordée",
  "ImageDownloaded": "Image téléchargée avec succès.",
  "Photoaddedcamera": "Photo ajoutée à la pellicule!",
  "Turnofflivelocation": "Désactiver la localisation en direct pour cette commande.",
  "Turnonlivelocation": "Activer la localisation en direct pour cette commande.",
  "OK": "OK",
  "OFFLiveLocation": "Localisation en direct désactivée",
  "ONLiveLocation": "Localisation en direct activée",
  "Overlimit": "Au-dessus de la limite!",
  "Unableopensettings": "Impossible d'ouvrir les paramètres",
  "Locationpermissiondenied": "Autorisation de localisation refusée",
  "TurnonLocationServices": "Activez les services de localisation pour autoriser",
  "determineyourlocation": "Pour déterminer votre emplacement.",
  "GotoSettings": "Aller aux paramètres",
  "DontUseLocation": "Ne pas utiliser l'emplacement",
  "Code": "Code",
  "scheduleerror": "Erreur d'horaire",
  "errrequestingtryagian": "Erreur lors de la demande, essayez à nouveau ..",
  "paymentCashonDelivery": "Votre mode de paiement est Paiement à la livraison, le montant à payer est",
  "confirmproceedorder": "Veuillez confirmer pour poursuivre la commande",
  "providervalidation": "Veuillez confirmer l'envoi de cette commande au fournisseur pour validation.",
  "Networkerror": "Erreur de connexion",
  "Adddiscountvalue": "Valeur de remise, Ajouter une valeur de remise inférieure ou égale au prix du produit",
  "Adddiscountvaluepercent": "Valeur de remise, Ajouter une valeur de remise entre 0 et 100 %",
  "error": "erreur",
  "clientsecret": "client secret",
  "cardholdername": "Entrez le nom du titulaire de la carte",
  "Paymentconfirmationerror": "Erreur de confirmation de paiement",
  "Filesize": "La taille du fichier dépasse 5 Mo, veuillez sélectionner un fichier de 5 Mo ou moins",
  "selectdatefirst": "Veuillez d'abord sélectionner la date.",
  "NoFileChosen": "Aucun fichier choisi",
  "Changeorderstatus": "Changer le statut de la commande à",
  "ReadyforDelivery": "Prêt pour la livraison",
  "Confirmationrequired": "Confirmation requise!",
  "confirmorderproceed": "Vous devez confirmer pour continuer.",
  "Notificationswitched": "Le paramètre de notification a été modifié avec succès",
  "somethingwentwrong": "Quelque chose s'est mal passé",
  "stripeerror": "Erreur Stripe",
  "enteremail": "Veuillez saisir votre adresse e-mail",
  "validemail": "Mettez une adresse email valide",
  "phonenumber": "Veuillez entrer votre numéro de téléphone",
  "ordernumber": "Veuillez entrer votre numéro de commande",
  "refundorder": "Veuillez entrer les détails de la commande de remboursement",
  "Somethingwentwrong": "Quelque chose s'est mal passé",
  "onPressUpload": "Télécharger",
  "errorgettingprovince": "Erreur lors de l'obtention de la province",
  "privacyPolicy": "politique de confidentialité",
  "SortBy": "Trier par",
  "resetError": "Le mot de passe doit comporter au moins 8 caractères et inclure au moins une lettre majuscule, une lettre minuscule, un chiffre et un caractère spécial.",
  "DeleteAccount": "Supprimer le compte",
  "ConfirmDeleteAccount": "Confirmer la suppression du compte",
  "DeleteAccountMsg": "Voulez-vous vraiment supprimer ce compte?",
  "DeleteSuccessfully": "Votre compte est supprimé avec succès",
  "ReadyToDelivery": "Prêt à être livré"
}
